{
    "url": "https://news.yahoo.co.jp/pickup/6531680",
    "title": "アメリカとウクライナ 来週会談へ - Yahoo!ニュース",
    "description": "Steve Holland［ワシントン　６日　ロイター］ - トランプ米政権のウィトコフ中東担当特使は６日、ウクライナと和平合意や停戦の枠組みを巡り協議しており、来週サウジアラビアでウクライナ当局者",
    "content": "現在JavaScriptが無効になっていますYahoo!ニュースのすべての機能を利用するためには、JavaScriptの設定を有効にしてください。JavaScriptの設定を変更する方法はこちら米・ウクライナ、来週サウジで会談の計画　和平合意枠組みなど協議へ＝高官ロイター228解説コメント228件記事全文を読むアメリカとウクライナ 来週会談へ3/7(金) 12:35ロイター米・ウクライナ、来週サウジで会談の計画　和平合意枠組みなど協議へ＝高官ロイター228解説コメント228件Steve Holland\n\n［ワシントン　６日　ロイター］ - トランプ米政権のウィトコフ中東担当特使は６日、ウクライナと和平合意や停戦の枠組みを巡り協議しており、来週サウジアラビアでウクライナ当局者と会談する計画と明らかにした。記事全文を読む詳しく知るゼレンスキー氏　来週の米高官協議に「意義深い会談になることを願う」出典：毎日新聞3/7(金)みんなの意見ウクライナ情勢について、あなたが最も気になることは何ですか？投票数：9,379票米国のウクライナ支援の行方42.3%欧州各国の対応26%停戦の時期や条件15%民間人の犠牲6.2%あなたの意見は？※ 統計に基づく世論調査ではありません。＊＊＊＊＊＊＊＊＊＊＊＊＊＊＊＊＊＊＊＊＊＊＊＊＊＊＊＊＊＊＊＊＊＊＊＊＊＊＊＊＊＊＊＊＊＊＊＊＊＊＊＊＊＊＊＊＊＊＊＊＊＊＊＊＊＊＊＊＊＊＊＊＊＊＊＊＊＊＊＊＊＊＊＊＊＊＊＊＊＊＊＊＊＊＊＊＊＊＊＊＊＊＊＊＊＊＊＊＊＊＊＊＊＊＊＊＊＊＊＊＊＊＊＊＊＊＊＊＊＊＊＊＊＊＊＊＊＊＊＊＊＊＊＊＊＊＊＊＊＊＊＊＊＊＊＊＊＊＊＊＊＊＊＊＊＊トピックス（国際）尹大統領の釈放決定 韓国地裁ゼレンスキー氏が停戦条件を提示アメリカとウクライナ 来週会談へトランプ氏、日米同盟に不満表明米 関税「1カ月猶予」の対象拡大ウ避難民在留資格取り消し計画 米デンマーク 手紙配達を今年で廃止ポケモン似 菓子8万ドル超で落札【3.11企画】東北や能登を寄付で応援支援を必要とする人のために寄付をお願いしますアクセスランキング（国際）1ラテン系女優の『白雪姫』に「低評価」１１０万人…結局、ロンドン試写会が中止に中央日報日本語版3/7(金)11:192ゼレンスキー氏、停戦条件を提示…ロシア外務省「何らかの猶予を与えることは受け入れられない」読売新聞オンライン3/7(金)11:393マスク氏の装いはOK？　　ホワイトハウス高官、返答窮す　米時事通信3/6(木)14:104トルドー加首相は「ばか者」　米財務長官時事通信3/7(金)9:475中国外相、台湾巡り日本に警告共同通信3/7(金)12:34動画アクセスランキング1原田宗典「靴下を選べなくなって出かけられなくなった」躁うつ病を経験して、今思うこと #今つらいあなたへYahoo!ニュース オリジナル Voice3/7(金)10:023:362「仕事行かへん…ええかげんにせえ」「大きな声で怒鳴っていた」公開手配の息子と過去トラブルか　タワマン高齢男女死傷MBSニュース3/7(金)11:500:503【速報】70代女性が路線バスの下敷きになり死亡　横浜市テレビ朝日系（ANN）3/7(金)13:040:544“安いのに高品質”進化するプライベートブランド（PB）商品、製造する大手メーカー側のメリットは?【Nスタ解説】TBS NEWS DIG Powered by JNN3/6(木)22:3210:175福島出身の東電社員、忘れられない「無力感」　挑んだ燃料デブリの取り出し　#知り続ける福島中央テレビ3/7(金)11:004:10",
    "images": [
        "https://news-pctr.c.yimg.jp/t/news-topics/images/tpc/2025/3/7/472783d20c39dfd81d9cf5e016075c18850514124a6df1df8969d38ac37848b6.jpg",
        "https://s.yimg.jp/c/logo/f/2.0/news_r_34_2x.png",
        "https://news-pctr.c.yimg.jp/t/news-topics/images/tpc/2025/3/7/1d02ddfe597061370ab6488d656701cff207c50f18931da4a77ede616bfcaa19.jpg",
        "https://news-pctr.c.yimg.jp/t/amd-img/20250307-00000006-mai-000-2-view.jpg?cx=53&cy=0&cw=533&ch=533&order=crop2resize&w=264&h=264&pri=l",
        "https://news-pctr.c.yimg.jp/t/amd-img/20250307-00000032-cnippou-000-1-view.jpg?w=264&h=264&cx=89&cy=0&cw=422&ch=422&fill=false&fmt=jpeg&exp=10800&order=c2r",
        "https://news-pctr.c.yimg.jp/t/amd-img/20250307-00050049-yom-000-14-view.jpg?w=264&h=264&cx=125&cy=0&cw=333&ch=333&fill=false&fmt=jpeg&exp=10800&order=c2r",
        "https://news-pctr.c.yimg.jp/t/amd-img/20250306-00000065-jij-000-13-view.jpg?w=264&h=264&cx=277&cy=0&cw=777&ch=777&fill=false&fmt=jpeg&exp=10800&order=c2r",
        "https://news-pctr.c.yimg.jp/t/amd-img/20250307-00000043-jij-000-10-view.jpg?w=264&h=264&cx=207&cy=0&cw=800&ch=800&fill=false&fmt=jpeg&exp=10800&order=c2r",
        "https://news-pctr.c.yimg.jp/r/iwiz-tpc/images/tpc/eternal/2017/10/27/1509081692_1427194511_1427194505_topics550x550.jpg",
        "https://news-pctr.c.yimg.jp/t/amd-img/20250307-00010000-ynewstalk-000-6-thumb.jpg?w=264&h=198&fill=false&fmt=jpeg&exp=10800",
        "https://news-pctr.c.yimg.jp/t/amd-img/20250307-00064154-mbsnews-000-4-thumb.jpg?w=264&h=149&fill=false&fmt=jpeg&exp=10800",
        "https://news-pctr.c.yimg.jp/t/amd-img/20250307-00000050-ann-000-11-thumb.jpg?w=264&h=149&fill=false&fmt=jpeg&exp=10800",
        "https://news-pctr.c.yimg.jp/t/amd-img/20250306-21773307-jnn-000-1-thumb.jpg?w=264&h=149&fill=false&fmt=jpeg&exp=10800",
        "https://news-pctr.c.yimg.jp/t/amd-img/20250307-00010000-fctg-000-2-thumb.jpg?w=264&h=149&fill=false&fmt=jpeg&exp=10800"
    ],
    "links": [
        "https://news.yahoo.co.jp/",
        "https://www.yahoo.co.jp/",
        "https://support.yahoo-net.jp/PccNews/s/",
        "https://news.yahoo.co.jp/users/me",
        "https://news.yahoo.co.jp/purchase",
        "https://news.yahoo.co.jp/settings/blocked-users",
        "https://news.yahoo.co.jp/",
        "https://news.yahoo.co.jp/flash",
        "https://news.yahoo.co.jp/live",
        "https://news.yahoo.co.jp/expert/",
        "https://news.yahoo.co.jp/original/",
        "https://news.yahoo.co.jp/polls/",
        "https://news.yahoo.co.jp/ranking/access/news",
        "https://news.yahoo.co.jp/paidnews?source=pc-common-glonav",
        "https://news.yahoo.co.jp/",
        "https://news.yahoo.co.jp/categories/domestic",
        "https://news.yahoo.co.jp/categories/world",
        "https://news.yahoo.co.jp/categories/business",
        "https://news.yahoo.co.jp/categories/entertainment",
        "https://news.yahoo.co.jp/categories/sports",
        "https://news.yahoo.co.jp/categories/it",
        "https://news.yahoo.co.jp/categories/science",
        "https://news.yahoo.co.jp/categories/life",
        "https://news.yahoo.co.jp/categories/local",
        "https://news.yahoo.co.jp/topics/top-picks",
        "https://support.yahoo-net.jp/noscript",
        "https://news.yahoo.co.jp/articles/2994f0355bf7c9d712bdeaabfc60ae4474b4cf8e",
        "https://news.yahoo.co.jp/articles/2994f0355bf7c9d712bdeaabfc60ae4474b4cf8e",
        "https://news.yahoo.co.jp/articles/2994f0355bf7c9d712bdeaabfc60ae4474b4cf8e/images/000",
        "https://news.yahoo.co.jp/articles/2994f0355bf7c9d712bdeaabfc60ae4474b4cf8e",
        "https://news.yahoo.co.jp/articles/2994f0355bf7c9d712bdeaabfc60ae4474b4cf8e",
        "https://x.com/intent/tweet?text=%E3%82%A2%E3%83%A1%E3%83%AA%E3%82%AB%E3%81%A8%E3%82%A6%E3%82%AF%E3%83%A9%E3%82%A4%E3%83%8A%20%E6%9D%A5%E9%80%B1%E4%BC%9A%E8%AB%87%E3%81%B8%0A%23Yahoo%E3%83%8B%E3%83%A5%E3%83%BC%E3%82%B9%0Ahttps%3A%2F%2Fnews.yahoo.co.jp%2Fpickup%2F6531680",
        "https://www.facebook.com/sharer?u=https://news.yahoo.co.jp/pickup/6531680",
        "https://news.yahoo.co.jp/articles/421f899e58d616c144942b6b3efbdb93ba2c34ce",
        "https://news.yahoo.co.jp/polls/50470",
        "https://news.yahoo.co.jp/topics/world",
        "https://news.yahoo.co.jp/pickup/6531695",
        "https://news.yahoo.co.jp/pickup/6531694",
        "https://news.yahoo.co.jp/pickup/6531680",
        "https://news.yahoo.co.jp/pickup/6531658",
        "https://news.yahoo.co.jp/pickup/6531642",
        "https://news.yahoo.co.jp/pickup/6531650",
        "https://news.yahoo.co.jp/pickup/6531673",
        "https://news.yahoo.co.jp/pickup/6531638",
        "https://yahoo.jp/diia-G",
        "https://news.yahoo.co.jp/ranking/access/news/world",
        "https://news.yahoo.co.jp/articles/b2a919706f50a465e8566e0815e18253f42ce6ab",
        "https://news.yahoo.co.jp/articles/545242562d0b2ecf02912e687e7a8500c2bb150a",
        "https://news.yahoo.co.jp/articles/4ef9f433b4199014c4075f3c4cbe8f9d00868041",
        "https://news.yahoo.co.jp/articles/9d5a1eefeb7949d18c43d6ecc1e3e8f4617525f6",
        "https://news.yahoo.co.jp/articles/16f129d2bb058ad5408e1d2ec890517c920b23ac",
        "https://news.yahoo.co.jp/ranking/access/video",
        "https://news.yahoo.co.jp/articles/b2b8fa063a0d925f8a133a164f5ac518e07564ca",
        "https://news.yahoo.co.jp/articles/453ea011ec95fd7d297c1b414159d763d08eb2b2",
        "https://news.yahoo.co.jp/articles/30343a76351085a794a374e7c4dc6c267c59f907",
        "https://news.yahoo.co.jp/articles/3abafc57ac434ed8c2b2d1c18aa1830b03e64aec",
        "https://news.yahoo.co.jp/articles/cf0601bb5f2e4d97f7ffbef831aff4cf5927a4ca",
        "https://news.yahoo.co.jp/promo/app/yjnews/",
        "https://www.facebook.com/yjnews",
        "https://x.com/YahooNewsTopics",
        "https://news.yahoo.co.jp/newshack/",
        "https://news.yahoo.co.jp/",
        "https://news.yahoo.co.jp/flash",
        "https://news.yahoo.co.jp/live",
        "https://news.yahoo.co.jp/expert/",
        "https://news.yahoo.co.jp/original/",
        "https://news.yahoo.co.jp/polls/",
        "https://news.yahoo.co.jp/ranking/access/news",
        "https://news.yahoo.co.jp/paidnews",
        "https://news.yahoo.co.jp/rss",
        "https://news.yahoo.co.jp/media",
        "https://www.lycorp.co.jp/ja/company/privacypolicy/",
        "https://privacy.lycorp.co.jp/ja/",
        "https://www.lycorp.co.jp/ja/company/terms/",
        "https://www.lycorp.co.jp/ja/company/mediastatement/",
        "https://news.yahoo.co.jp/info/news-operation-policy",
        "https://support.yahoo-net.jp/PccNews/s/article/H000006460",
        "https://news.yahoo.co.jp/info/commercial-transactions",
        "https://support.yahoo-net.jp/voc/s/news",
        "https://support.yahoo-net.jp/PccNews/s/"
    ]
}